[
null,
{"id":1,"expanded":false,"name":"Alchemy Basement","order":2,"parentId":0,"scrollX":973.1999999999999,"scrollY":559.8},
{"id":2,"expanded":false,"name":"Alchemy Lab","order":3,"parentId":1,"scrollX":973.1999999999999,"scrollY":559.8,"quick":false},
{"id":3,"expanded":false,"name":"Academy outside","order":14,"parentId":0,"scrollX":973.1999999999999,"scrollY":559.8,"quick":false},
{"id":4,"expanded":false,"name":"Alchemy Hall","order":4,"parentId":1,"scrollX":1081.3333333333333,"scrollY":622,"quick":false},
{"id":5,"expanded":false,"name":"Starting Classroom","order":8,"parentId":18,"scrollX":720.8888888888889,"scrollY":414.6666666666667,"quick":false},
{"id":6,"expanded":false,"name":"Graveyard","order":15,"parentId":0,"scrollX":973.1999999999999,"scrollY":559.8,"quick":false},
{"id":7,"expanded":false,"name":"Mom","order":16,"parentId":6,"scrollX":973.1999999999999,"scrollY":559.8,"quick":false},
{"id":8,"expanded":false,"name":"Forbidden Hole","order":19,"parentId":0,"scrollX":1081.3333333333333,"scrollY":622,"quick":false},
{"id":9,"expanded":false,"name":"Libaray","order":5,"parentId":4,"scrollX":1216.5,"scrollY":789.75,"quick":false},
{"id":10,"expanded":false,"name":"Joy's House","order":21,"parentId":12,"scrollX":973.1999999999999,"scrollY":559.8,"quick":false},
{"id":11,"expanded":false,"name":"Joy's Alter","order":22,"parentId":10,"scrollX":0,"scrollY":0,"quick":false},
{"id":12,"expanded":false,"name":"Blackridge Homes","order":20,"parentId":0,"scrollX":982.8,"scrollY":640.1999999999999,"quick":false},
{"id":13,"expanded":false,"name":"Pathway","order":23,"parentId":0,"scrollX":973.1999999999999,"scrollY":559.8,"quick":false},
{"id":14,"expanded":false,"name":"Testing","order":1,"parentId":0,"scrollX":973.1999999999999,"scrollY":559.8,"quick":false},
{"id":15,"expanded":false,"name":"Anandamide Farm","order":17,"parentId":6,"scrollX":0,"scrollY":0,"quick":false},
{"id":16,"expanded":false,"name":"MAP016","order":18,"parentId":6,"scrollX":0,"scrollY":0,"quick":false},
{"id":17,"expanded":false,"name":"Hallway","order":6,"parentId":4,"scrollX":720.8888888888889,"scrollY":414.6666666666667,"quick":false},
{"id":18,"expanded":false,"name":"Hallway2","order":7,"parentId":17,"scrollX":973.1999999999999,"scrollY":559.8,"quick":false},
{"id":19,"expanded":false,"name":"Herbalism & Botany","order":9,"parentId":18,"scrollX":811,"scrollY":466.5,"quick":false},
{"id":20,"expanded":false,"name":"Shadow Defence","order":10,"parentId":18,"scrollX":720.8888888888889,"scrollY":414.6666666666667,"quick":false},
{"id":21,"expanded":false,"name":"Familiar Bonding","order":11,"parentId":18,"scrollX":0,"scrollY":0,"quick":false},
{"id":22,"expanded":true,"name":"Spellcasting & Rituals","order":12,"parentId":17,"scrollX":0,"scrollY":0,"quick":false},
{"id":23,"expanded":false,"name":"MAP023","order":13,"parentId":22,"scrollX":0,"scrollY":0,"quick":false}
]